epochrony/__init__.py
epochrony/base.py
epochrony-0.0.1.dist-info/METADATA
epochrony-0.0.1.dist-info/WHEEL
epochrony-0.0.1.dist-info/licenses/LICENSE
epochrony-0.0.1.dist-info/RECORD
