Metadata-Version: 2.3
Name: epochrony
Version: 0.0.1
Summary: Time and date scheduling service
Project-URL: Homepage, https://github.com/voquis/epochrony
Project-URL: Issues, https://github.com/voquis/epochrony/issues
Author-email: Voquis Limited <opensource@voquis.com>
License-File: LICENSE
Classifier: License :: OSI Approved :: MIT License
Classifier: Operating System :: OS Independent
Classifier: Programming Language :: Python :: 3
Requires-Python: >=3.10
Provides-Extra: dev
Requires-Dist: black; extra == 'dev'
Requires-Dist: build; extra == 'dev'
Requires-Dist: flake8; extra == 'dev'
Requires-Dist: pylint; extra == 'dev'
Requires-Dist: pytest; extra == 'dev'
Requires-Dist: pytest-cov; extra == 'dev'
Requires-Dist: twine; extra == 'dev'
